scoutmcp/__init__.py
scoutmcp/__main__.py
scoutmcp/config.py
scoutmcp/exceptions.py
scoutmcp/native_mcp_server.py
scoutsdk/__init__.py
scoutsdk/py.typed
scoutsdk/agents/__init__.py
scoutsdk/agents/scout_agent.py
scoutsdk/agents/scout_agent_runner.py
scoutsdk/api/__init__.py
scoutsdk/api/api.py
scoutsdk/api/assistants.py
scoutsdk/api/audio.py
scoutsdk/api/chat.py
scoutsdk/api/chat_tools_helper.py
scoutsdk/api/constants.py
scoutsdk/api/conversations.py
scoutsdk/api/current_assistant.py
scoutsdk/api/deprecated.py
scoutsdk/api/function_progress.py
scoutsdk/api/image.py
scoutsdk/api/project_helpers.py
scoutsdk/api/protected.py
scoutsdk/api/py.typed
scoutsdk/api/request_utils.py
scoutsdk/api/retry_config.py
scoutsdk/api/skills.py
scoutsdk/api/utils.py
scoutsdk/api/types/__init__.py
scoutsdk/api/types/assistants.py
scoutsdk/api/types/chat.py
scoutsdk/api/types/images.py
scoutsdk/cli/__init__.py
scoutsdk/cli/__main__.py
scoutsdk/cli/cli.py
scoutsdk/cli/config.py
scoutsdk/cli/error_handler.py
scoutsdk/cli/py.typed
scoutsdk/cli/types.py
scoutsdk/cli/utils.py
scoutsdk/cli/modules/__init__.py
scoutsdk/cli/modules/apps_module.py
scoutsdk/cli/modules/assistants_module.py
scoutsdk/cli/modules/base_module.py
scoutsdk/cli/modules/chat_completion_module.py
scoutsdk/cli/modules/functions_module.py
scoutsdk/cli/modules/mcp_module.py
scoutsdk/cli/modules/pkg_module.py
scoutsdk/cli/modules/skills_module.py
scoutsdk/cli/modules/skills_sync_module.py
scoutsdk/cli/modules/sync_module.py
scoutsdk/crawlers/__init__.py
scoutsdk/crawlers/crawlers.py
scoutsdk/crawlers/indexers.py
scoutsdk/crawlers/crawlers_impl/__init__.py
scoutsdk/crawlers/crawlers_impl/sharepoint_crawler.py
scoutsdk/crawlers/indexers_impl/__init__.py
scoutsdk/crawlers/indexers_impl/spreadsheet_url_indexer.py
scoutsdk/crawlers/indexers_impl/summary_url_indexer.py
scoutsdk/crawlers/indexers_impl/text_file_indexer.py
scoutsdk/crawlers/indexers_impl/utils/__init__.py
scoutsdk/crawlers/indexers_impl/utils/assistant_data_utils.py
scoutsdk-0.2.4.dist-info/METADATA
scoutsdk-0.2.4.dist-info/WHEEL
scoutsdk-0.2.4.dist-info/entry_points.txt
scoutsdk-0.2.4.dist-info/top_level.txt
scoutsdk-0.2.4.dist-info/RECORD
