Metadata-Version: 2.4
Name: scoutsdk
Version: 0.2.4
Summary: Python package for scoutsdk
Author-email: Mirego <info@mirego.com>
Requires-Python: >=3.11
Requires-Dist: requests>=2.32.2
Requires-Dist: pydantic>=2.11.7
Requires-Dist: python-dotenv>=1.0.1
Requires-Dist: jsonschema>=4.23.0
Requires-Dist: tenacity>=9.0.0
Provides-Extra: dev
Requires-Dist: pytest; extra == "dev"
Requires-Dist: mypy; extra == "dev"
Requires-Dist: ruff; extra == "dev"
Provides-Extra: mcp
Requires-Dist: mcp>=1.13.1; extra == "mcp"
